[
  {
    "id": "iso-ff0c3b65-e2e2-4aea-bc8c-69509f535216",
    "isoNumeric": null,
    "alpha2": "AT",
    "alpha3": "AUT",
    "longName": "the Republic of Austria",
    "name": "Austria",
    "independent": false,
    "statusName": "officially-assigned",
    "system": "iso",
    "systemAlias": null,
    "systemAlpha2": null,
    "systemAlpha3": null,
    "systemLongName": null,
    "effectiveAlias": "Austria",
    "effectiveAlpha2": "AT",
    "effectiveAlpha3": "AUT",
    "effectiveLongName": "the Republic of Austria",
    "classifiers": [
      "EU",
      "EEA",
      "CTC"
    ],
    "internalClassifiers": []
  },
  {
    "id": "iso-93335cc8-7cab-4fc1-9cfd-db981927691a",
    "isoNumeric": null,
    "alpha2": "BE",
    "alpha3": "BEL",
    "longName": "the Kingdom of Belgium",
    "name": "Belgium",
    "independent": false,
    "statusName": "officially-assigned",
    "system": "iso",
    "systemAlias": null,
    "systemAlpha2": null,
    "systemAlpha3": null,
    "systemLongName": null,
    "effectiveAlias": "Belgium",
    "effectiveAlpha2": "BE",
    "effectiveAlpha3": "BEL",
    "effectiveLongName": "the Kingdom of Belgium",
    "classifiers": [
      "EU",
      "EEA",
      "CTC"
    ],
    "internalClassifiers": []
  },
  {
    "id": "iso-ba634826-da28-4489-9961-abeb395c6a73",
    "isoNumeric": null,
    "alpha2": "BG",
    "alpha3": "BGR",
    "longName": "the Republic of Bulgaria",
    "name": "Bulgaria",
    "independent": false,
    "statusName": "officially-assigned",
    "system": "iso",
    "systemAlias": null,
    "systemAlpha2": null,
    "systemAlpha3": null,
    "systemLongName": null,
    "effectiveAlias": "Bulgaria",
    "effectiveAlpha2": "BG",
    "effectiveAlpha3": "BGR",
    "effectiveLongName": "the Republic of Bulgaria",
    "classifiers": [
      "EU",
      "EEA",
      "CTC"
    ],
    "internalClassifiers": []
  },
  {
    "id": "iso-a46c66be-f108-4892-8db0-a39bdcd06e49",
    "isoNumeric": null,
    "alpha2": "HR",
    "alpha3": "HRV",
    "longName": "the Republic of Croatia",
    "name": "Croatia",
    "independent": false,
    "statusName": "officially-assigned",
    "system": "iso",
    "systemAlias": null,
    "systemAlpha2": null,
    "systemAlpha3": null,
    "systemLongName": null,
    "effectiveAlias": "Croatia",
    "effectiveAlpha2": "HR",
    "effectiveAlpha3": "HRV",
    "effectiveLongName": "the Republic of Croatia",
    "classifiers": [
      "EU",
      "EEA",
      "CTC"
    ],
    "internalClassifiers": []
  },
  {
    "id": "iso-22692319-d0d8-4068-aa0f-c3344f1e8042",
    "isoNumeric": null,
    "alpha2": "CY",
    "alpha3": "CYP",
    "longName": "the Republic of Cyprus",
    "name": "Cyprus",
    "independent": false,
    "statusName": "officially-assigned",
    "system": "iso",
    "systemAlias": null,
    "systemAlpha2": null,
    "systemAlpha3": null,
    "systemLongName": null,
    "effectiveAlias": "Cyprus",
    "effectiveAlpha2": "CY",
    "effectiveAlpha3": "CYP",
    "effectiveLongName": "the Republic of Cyprus",
    "classifiers": [
      "EU",
      "EEA",
      "CTC"
    ],
    "internalClassifiers": []
  },
  {
    "id": "iso-39cf9f4e-3cca-497a-8e3b-97659f7f13a3",
    "isoNumeric": null,
    "alpha2": "CZ",
    "alpha3": "CZE",
    "longName": "the Czech Republic",
    "name": "Czechia",
    "independent": false,
    "statusName": "officially-assigned",
    "system": "iso",
    "systemAlias": null,
    "systemAlpha2": null,
    "systemAlpha3": null,
    "systemLongName": null,
    "effectiveAlias": "Czechia",
    "effectiveAlpha2": "CZ",
    "effectiveAlpha3": "CZE",
    "effectiveLongName": "the Czech Republic",
    "classifiers": [
      "EU",
      "EEA",
      "CTC"
    ],
    "internalClassifiers": []
  },
  {
    "id": "iso-3fc5639d-d536-4dce-a4b4-4407913335f5",
    "isoNumeric": null,
    "alpha2": "DK",
    "alpha3": "DNK",
    "longName": "the Kingdom of Denmark",
    "name": "Denmark",
    "independent": false,
    "statusName": "officially-assigned",
    "system": "iso",
    "systemAlias": null,
    "systemAlpha2": null,
    "systemAlpha3": null,
    "systemLongName": null,
    "effectiveAlias": "Denmark",
    "effectiveAlpha2": "DK",
    "effectiveAlpha3": "DNK",
    "effectiveLongName": "the Kingdom of Denmark",
    "classifiers": [
      "EU",
      "EEA",
      "CTC"
    ],
    "internalClassifiers": []
  },
  {
    "id": "iso-a1e37cf2-9cb4-47d3-b663-74ac0bc04822",
    "isoNumeric": null,
    "alpha2": "EE",
    "alpha3": "EST",
    "longName": "the Republic of Estonia",
    "name": "Estonia",
    "independent": false,
    "statusName": "officially-assigned",
    "system": "iso",
    "systemAlias": null,
    "systemAlpha2": null,
    "systemAlpha3": null,
    "systemLongName": null,
    "effectiveAlias": "Estonia",
    "effectiveAlpha2": "EE",
    "effectiveAlpha3": "EST",
    "effectiveLongName": "the Republic of Estonia",
    "classifiers": [
      "EU",
      "EEA",
      "CTC"
    ],
    "internalClassifiers": []
  },
  {
    "id": "iso-69ff6911-ceab-4b55-9ac1-7cfa38bf11d4",
    "isoNumeric": null,
    "alpha2": "FI",
    "alpha3": "FIN",
    "longName": "the Republic of Finland",
    "name": "Finland",
    "independent": false,
    "statusName": "officially-assigned",
    "system": "iso",
    "systemAlias": null,
    "systemAlpha2": null,
    "systemAlpha3": null,
    "systemLongName": null,
    "effectiveAlias": "Finland",
    "effectiveAlpha2": "FI",
    "effectiveAlpha3": "FIN",
    "effectiveLongName": "the Republic of Finland",
    "classifiers": [
      "EU",
      "EEA",
      "CTC"
    ],
    "internalClassifiers": []
  },
  {
    "id": "iso-59db9a0d-de38-4842-a370-4b9912e38bb6",
    "isoNumeric": null,
    "alpha2": "FR",
    "alpha3": "FRA",
    "longName": "the French Republic",
    "name": "France",
    "independent": false,
    "statusName": "officially-assigned",
    "system": "iso",
    "systemAlias": null,
    "systemAlpha2": null,
    "systemAlpha3": null,
    "systemLongName": null,
    "effectiveAlias": "France",
    "effectiveAlpha2": "FR",
    "effectiveAlpha3": "FRA",
    "effectiveLongName": "the French Republic",
    "classifiers": [
      "EU",
      "EEA",
      "CTC"
    ],
    "internalClassifiers": []
  },
  {
    "id": "iso-52869b53-bee2-41d0-b73e-5d0c834df241",
    "isoNumeric": null,
    "alpha2": "DE",
    "alpha3": "DEU",
    "longName": "the Federal Republic of Germany",
    "name": "Germany",
    "independent": false,
    "statusName": "officially-assigned",
    "system": "iso",
    "systemAlias": null,
    "systemAlpha2": null,
    "systemAlpha3": null,
    "systemLongName": null,
    "effectiveAlias": "Germany",
    "effectiveAlpha2": "DE",
    "effectiveAlpha3": "DEU",
    "effectiveLongName": "the Federal Republic of Germany",
    "classifiers": [
      "EU",
      "EEA",
      "CTC"
    ],
    "internalClassifiers": []
  },
  {
    "id": "iso-26700432-d7e1-4542-994c-0b81ad34ca81",
    "isoNumeric": null,
    "alpha2": "GR",
    "alpha3": "GRC",
    "longName": "the Hellenic Republic",
    "name": "Greece",
    "independent": false,
    "statusName": "officially-assigned",
    "system": "iso",
    "systemAlias": null,
    "systemAlpha2": null,
    "systemAlpha3": null,
    "systemLongName": null,
    "effectiveAlias": "Greece",
    "effectiveAlpha2": "GR",
    "effectiveAlpha3": "GRC",
    "effectiveLongName": "the Hellenic Republic",
    "classifiers": [
      "EU",
      "EEA",
      "CTC"
    ],
    "internalClassifiers": []
  },
  {
    "id": "iso-07b89f5d-64bd-4b58-8106-31f9571558a2",
    "isoNumeric": null,
    "alpha2": "HU",
    "alpha3": "HUN",
    "longName": "Hungary",
    "name": "Hungary",
    "independent": false,
    "statusName": "officially-assigned",
    "system": "iso",
    "systemAlias": null,
    "systemAlpha2": null,
    "systemAlpha3": null,
    "systemLongName": null,
    "effectiveAlias": "Hungary",
    "effectiveAlpha2": "HU",
    "effectiveAlpha3": "HUN",
    "effectiveLongName": "Hungary",
    "classifiers": [
      "EU",
      "EEA",
      "CTC"
    ],
    "internalClassifiers": []
  },
  {
    "id": "iso-6deb37fd-762d-4239-8c2c-cf97c9056070",
    "isoNumeric": null,
    "alpha2": "IS",
    "alpha3": "ISL",
    "longName": "the Republic of Iceland",
    "name": "Iceland",
    "independent": false,
    "statusName": "officially-assigned",
    "system": "iso",
    "systemAlias": null,
    "systemAlpha2": null,
    "systemAlpha3": null,
    "systemLongName": null,
    "effectiveAlias": "Iceland",
    "effectiveAlpha2": "IS",
    "effectiveAlpha3": "ISL",
    "effectiveLongName": "the Republic of Iceland",
    "classifiers": [
      "EFTA",
      "EEA",
      "CTC"
    ],
    "internalClassifiers": []
  },
  {
    "id": "iso-893b78f5-00b7-438d-88b3-04d900045a9e",
    "isoNumeric": null,
    "alpha2": "IE",
    "alpha3": "IRL",
    "longName": "Ireland",
    "name": "Ireland",
    "independent": false,
    "statusName": "officially-assigned",
    "system": "iso",
    "systemAlias": null,
    "systemAlpha2": null,
    "systemAlpha3": null,
    "systemLongName": null,
    "effectiveAlias": "Ireland",
    "effectiveAlpha2": "IE",
    "effectiveAlpha3": "IRL",
    "effectiveLongName": "Ireland",
    "classifiers": [
      "EU",
      "EEA",
      "CTC"
    ],
    "internalClassifiers": []
  },
  {
    "id": "iso-5e76caf7-5bde-479d-8895-ab3d557abaa0",
    "isoNumeric": null,
    "alpha2": "IT",
    "alpha3": "ITA",
    "longName": "the Republic of Italy",
    "name": "Italy",
    "independent": false,
    "statusName": "officially-assigned",
    "system": "iso",
    "systemAlias": null,
    "systemAlpha2": null,
    "systemAlpha3": null,
    "systemLongName": null,
    "effectiveAlias": "Italy",
    "effectiveAlpha2": "IT",
    "effectiveAlpha3": "ITA",
    "effectiveLongName": "the Republic of Italy",
    "classifiers": [
      "EU",
      "EEA",
      "CTC"
    ],
    "internalClassifiers": []
  },
  {
    "id": "iso-14da9a56-a90e-425a-8d60-b2ac3a6ca24f",
    "isoNumeric": null,
    "alpha2": "LV",
    "alpha3": "LVA",
    "longName": "the Republic of Latvia",
    "name": "Latvia",
    "independent": false,
    "statusName": "officially-assigned",
    "system": "iso",
    "systemAlias": null,
    "systemAlpha2": null,
    "systemAlpha3": null,
    "systemLongName": null,
    "effectiveAlias": "Latvia",
    "effectiveAlpha2": "LV",
    "effectiveAlpha3": "LVA",
    "effectiveLongName": "the Republic of Latvia",
    "classifiers": [
      "EU",
      "EEA",
      "CTC"
    ],
    "internalClassifiers": []
  },
  {
    "id": "iso-bb417224-3d01-426d-982b-16e59978e075",
    "isoNumeric": null,
    "alpha2": "LI",
    "alpha3": "LIE",
    "longName": "the Principality of Liechtenstein",
    "name": "Liechtenstein",
    "independent": false,
    "statusName": "officially-assigned",
    "system": "iso",
    "systemAlias": null,
    "systemAlpha2": null,
    "systemAlpha3": null,
    "systemLongName": null,
    "effectiveAlias": "Liechtenstein",
    "effectiveAlpha2": "LI",
    "effectiveAlpha3": "LIE",
    "effectiveLongName": "the Principality of Liechtenstein",
    "classifiers": [
      "EFTA",
      "EEA",
      "CTC"
    ],
    "internalClassifiers": []
  },
  {
    "id": "iso-b737eb58-49e4-4a5c-9e97-ced0c4da3fdb",
    "isoNumeric": null,
    "alpha2": "LT",
    "alpha3": "LTU",
    "longName": "the Republic of Lithuania",
    "name": "Lithuania",
    "independent": false,
    "statusName": "officially-assigned",
    "system": "iso",
    "systemAlias": null,
    "systemAlpha2": null,
    "systemAlpha3": null,
    "systemLongName": null,
    "effectiveAlias": "Lithuania",
    "effectiveAlpha2": "LT",
    "effectiveAlpha3": "LTU",
    "effectiveLongName": "the Republic of Lithuania",
    "classifiers": [
      "EU",
      "EEA",
      "CTC"
    ],
    "internalClassifiers": []
  },
  {
    "id": "iso-9641942d-2465-436c-89bb-189faf85e671",
    "isoNumeric": null,
    "alpha2": "LU",
    "alpha3": "LUX",
    "longName": "the Grand Duchy of Luxembourg",
    "name": "Luxembourg",
    "independent": false,
    "statusName": "officially-assigned",
    "system": "iso",
    "systemAlias": null,
    "systemAlpha2": null,
    "systemAlpha3": null,
    "systemLongName": null,
    "effectiveAlias": "Luxembourg",
    "effectiveAlpha2": "LU",
    "effectiveAlpha3": "LUX",
    "effectiveLongName": "the Grand Duchy of Luxembourg",
    "classifiers": [
      "EU",
      "EEA",
      "CTC"
    ],
    "internalClassifiers": []
  },
  {
    "id": "iso-4247bcf4-0c24-43ec-8824-c29019ea92d3",
    "isoNumeric": null,
    "alpha2": "MT",
    "alpha3": "MLT",
    "longName": "the Republic of Malta",
    "name": "Malta",
    "independent": false,
    "statusName": "officially-assigned",
    "system": "iso",
    "systemAlias": null,
    "systemAlpha2": null,
    "systemAlpha3": null,
    "systemLongName": null,
    "effectiveAlias": "Malta",
    "effectiveAlpha2": "MT",
    "effectiveAlpha3": "MLT",
    "effectiveLongName": "the Republic of Malta",
    "classifiers": [
      "EU",
      "EEA",
      "CTC"
    ],
    "internalClassifiers": []
  },
  {
    "id": "iso-6008b82b-ae29-46f0-83bf-029aed5ab38e",
    "isoNumeric": null,
    "alpha2": "NL",
    "alpha3": "NLD",
    "longName": "the Kingdom of the Netherlands",
    "name": "Netherlands (the)",
    "independent": false,
    "statusName": "officially-assigned",
    "system": "iso",
    "systemAlias": null,
    "systemAlpha2": null,
    "systemAlpha3": null,
    "systemLongName": null,
    "effectiveAlias": "Netherlands (the)",
    "effectiveAlpha2": "NL",
    "effectiveAlpha3": "NLD",
    "effectiveLongName": "the Kingdom of the Netherlands",
    "classifiers": [
      "EU",
      "EEA",
      "CTC"
    ],
    "internalClassifiers": []
  },
  {
    "id": "iso-540a7ebf-cb3c-4df3-9a03-264da7f32b09",
    "isoNumeric": null,
    "alpha2": "NO",
    "alpha3": "NOR",
    "longName": "the Kingdom of Norway",
    "name": "Norway",
    "independent": false,
    "statusName": "officially-assigned",
    "system": "iso",
    "systemAlias": null,
    "systemAlpha2": null,
    "systemAlpha3": null,
    "systemLongName": null,
    "effectiveAlias": "Norway",
    "effectiveAlpha2": "NO",
    "effectiveAlpha3": "NOR",
    "effectiveLongName": "the Kingdom of Norway",
    "classifiers": [
      "EFTA",
      "EEA",
      "CTC"
    ],
    "internalClassifiers": []
  },
  {
    "id": "iso-4ba722d5-fcfb-4d88-8c39-7731128db677",
    "isoNumeric": null,
    "alpha2": "PL",
    "alpha3": "POL",
    "longName": "the Republic of Poland",
    "name": "Poland",
    "independent": false,
    "statusName": "officially-assigned",
    "system": "iso",
    "systemAlias": null,
    "systemAlpha2": null,
    "systemAlpha3": null,
    "systemLongName": null,
    "effectiveAlias": "Poland",
    "effectiveAlpha2": "PL",
    "effectiveAlpha3": "POL",
    "effectiveLongName": "the Republic of Poland",
    "classifiers": [
      "EU",
      "EEA",
      "CTC"
    ],
    "internalClassifiers": []
  },
  {
    "id": "iso-5b83254f-631c-4254-b12a-134db9271762",
    "isoNumeric": null,
    "alpha2": "PT",
    "alpha3": "PRT",
    "longName": "the Portuguese Republic",
    "name": "Portugal",
    "independent": false,
    "statusName": "officially-assigned",
    "system": "iso",
    "systemAlias": null,
    "systemAlpha2": null,
    "systemAlpha3": null,
    "systemLongName": null,
    "effectiveAlias": "Portugal",
    "effectiveAlpha2": "PT",
    "effectiveAlpha3": "PRT",
    "effectiveLongName": "the Portuguese Republic",
    "classifiers": [
      "EU",
      "EEA",
      "CTC"
    ],
    "internalClassifiers": []
  },
  {
    "id": "iso-ac5ac950-cd54-4f6b-8c25-8ca87d1642e1",
    "isoNumeric": null,
    "alpha2": "RO",
    "alpha3": "ROU",
    "longName": "Romania",
    "name": "Romania",
    "independent": false,
    "statusName": "officially-assigned",
    "system": "iso",
    "systemAlias": null,
    "systemAlpha2": null,
    "systemAlpha3": null,
    "systemLongName": null,
    "effectiveAlias": "Romania",
    "effectiveAlpha2": "RO",
    "effectiveAlpha3": "ROU",
    "effectiveLongName": "Romania",
    "classifiers": [
      "EU",
      "EEA",
      "CTC"
    ],
    "internalClassifiers": []
  },
  {
    "id": "iso-47d6f8a4-b6ba-474f-bd91-a550bc8c0c5c",
    "isoNumeric": null,
    "alpha2": "SK",
    "alpha3": "SVK",
    "longName": "the Slovak Republic",
    "name": "Slovakia",
    "independent": false,
    "statusName": "officially-assigned",
    "system": "iso",
    "systemAlias": null,
    "systemAlpha2": null,
    "systemAlpha3": null,
    "systemLongName": null,
    "effectiveAlias": "Slovakia",
    "effectiveAlpha2": "SK",
    "effectiveAlpha3": "SVK",
    "effectiveLongName": "the Slovak Republic",
    "classifiers": [
      "EU",
      "EEA",
      "CTC"
    ],
    "internalClassifiers": []
  },
  {
    "id": "iso-f101795d-25f3-45be-9343-05810a41a2d4",
    "isoNumeric": null,
    "alpha2": "SI",
    "alpha3": "SVN",
    "longName": "the Republic of Slovenia",
    "name": "Slovenia",
    "independent": false,
    "statusName": "officially-assigned",
    "system": "iso",
    "systemAlias": null,
    "systemAlpha2": null,
    "systemAlpha3": null,
    "systemLongName": null,
    "effectiveAlias": "Slovenia",
    "effectiveAlpha2": "SI",
    "effectiveAlpha3": "SVN",
    "effectiveLongName": "the Republic of Slovenia",
    "classifiers": [
      "EU",
      "EEA",
      "CTC"
    ],
    "internalClassifiers": []
  },
  {
    "id": "iso-e30948bc-b150-4185-912c-611d7a7b8328",
    "isoNumeric": null,
    "alpha2": "ES",
    "alpha3": "ESP",
    "longName": "the Kingdom of Spain",
    "name": "Spain",
    "independent": false,
    "statusName": "officially-assigned",
    "system": "iso",
    "systemAlias": null,
    "systemAlpha2": null,
    "systemAlpha3": null,
    "systemLongName": null,
    "effectiveAlias": "Spain",
    "effectiveAlpha2": "ES",
    "effectiveAlpha3": "ESP",
    "effectiveLongName": "the Kingdom of Spain",
    "classifiers": [
      "EU",
      "EEA",
      "CTC"
    ],
    "internalClassifiers": []
  },
  {
    "id": "iso-e4df87b8-d5b6-416a-ae9c-b6584ec7dd8a",
    "isoNumeric": null,
    "alpha2": "SE",
    "alpha3": "SWE",
    "longName": "the Kingdom of Sweden",
    "name": "Sweden",
    "independent": false,
    "statusName": "officially-assigned",
    "system": "iso",
    "systemAlias": null,
    "systemAlpha2": null,
    "systemAlpha3": null,
    "systemLongName": null,
    "effectiveAlias": "Sweden",
    "effectiveAlpha2": "SE",
    "effectiveAlpha3": "SWE",
    "effectiveLongName": "the Kingdom of Sweden",
    "classifiers": [
      "EU",
      "EEA",
      "CTC"
    ],
    "internalClassifiers": []
  }
]